latex2sympy2_extended/__init__.py
latex2sympy2_extended/antlr_parser.py
latex2sympy2_extended/latex2sympy2.py
latex2sympy2_extended/logic.py
latex2sympy2_extended/math_normalization.py
latex2sympy2_extended/sets.py
latex2sympy2_extended/symbols.py
latex2sympy2_extended/gen/antlr4_11_0/PSLexer.py
latex2sympy2_extended/gen/antlr4_11_0/PSListener.py
latex2sympy2_extended/gen/antlr4_11_0/PSParser.py
latex2sympy2_extended/gen/antlr4_13_2/PSLexer.py
latex2sympy2_extended/gen/antlr4_13_2/PSListener.py
latex2sympy2_extended/gen/antlr4_13_2/PSParser.py
latex2sympy2_extended/gen/antlr4_9_3/PSLexer.py
latex2sympy2_extended/gen/antlr4_9_3/PSListener.py
latex2sympy2_extended/gen/antlr4_9_3/PSParser.py
latex2sympy2_extended-1.0.9.dist-info/LICENSE.txt
latex2sympy2_extended-1.0.9.dist-info/METADATA
latex2sympy2_extended-1.0.9.dist-info/WHEEL
latex2sympy2_extended-1.0.9.dist-info/top_level.txt
latex2sympy2_extended-1.0.9.dist-info/RECORD
