Metadata-Version: 2.2
Name: latex2sympy2_extended
Version: 1.0.9
Summary: Convert LaTeX math to SymPy expressions
Author-email: Hynek Kydlíček <hynek.kydlicek@huggingface.co>
License: MIT
Project-URL: Homepage, https://github.com/OrangeX4/latex2sympy2
Project-URL: Repository, https://github.com/OrangeX4/latex2sympy2.git
Requires-Python: >=3.10
License-File: LICENSE.txt
Requires-Dist: sympy
Requires-Dist: antlr4-python3-runtime<=4.13.2,>=4.9.3
Provides-Extra: dev
Requires-Dist: pytest; extra == "dev"
Provides-Extra: antlr4-9-3
Requires-Dist: antlr4-python3-runtime==4.9.3; extra == "antlr4-9-3"
Provides-Extra: antlr4-11-0
Requires-Dist: antlr4-python3-runtime==4.11.0; extra == "antlr4-11-0"
Provides-Extra: antlr4-13-2
Requires-Dist: antlr4-python3-runtime==4.13.2; extra == "antlr4-13-2"
